briefly/__init__.py
briefly/cli.py
briefly/py.typed
briefly/fonts/Inter-Bold.ttf
briefly/fonts/Inter-Italic.ttf
briefly/fonts/Inter-Regular.ttf
briefly/fonts/MaterialIcons-Regular.ttf
briefly/model/__init__.py
briefly/model/style.py
briefly/rendering/__init__.py
briefly/rendering/font_spec.py
briefly/rendering/graphs.py
briefly/rendering/icons.py
briefly/rendering/pdf_generator.py
briefly-0.3.0.dist-info/METADATA
briefly-0.3.0.dist-info/WHEEL
briefly-0.3.0.dist-info/entry_points.txt
briefly-0.3.0.dist-info/top_level.txt
briefly-0.3.0.dist-info/RECORD
